Workbook

Sheet Inputs
A1: Final Model for Euro Challenge Viewing
A2: Lithuania Retention Pipeline - Final Eurostat-Baseline Model
A4: This workbook matches the final agreed model logic: EC/Eurostat-style baseline, policy measured as improvement relative to baseline, and family support as a tertiary module.
A6: Core demographic inputs
A7: Start year | B7: 2025
A8: End year | B8: 2050
A9: Starting population | B9: 2890000
A10: Starting working-age population | B10: 1750000
A11: Starting old-age population | B11: 560000
A12: Baseline annual total-population decline | B12: 0.0085955457
A13: Baseline annual working-age decline | B13: 0.012509527
A14: Annual old-age population growth | B14: 0.011156217
A15: Official baseline anchors
A17: 2050 population baseline anchor | B17: 2329000
A18: 2050 old-age dependency baseline anchor | B18: 0.579
A20: Policy engine inputs (annual, before scenario scaling)
A21: Immigrant entrants ages 18–34 helped by policy | B21: 3500
A22: Returning Lithuanians ages 18–34 helped by policy | B22: 1000
A23: Priority-sector graduates retained by policy | B23: 600
A24: Retention rate on policy entrants | B24: 0.7
A25: Annual exits from retained pool | B25: 800
A26: Additional parents kept in labor force | B26: 450
A27: Base net retained contributors per year | B27: =SUM(B21:B23)*B24-B25 -> 2770
A29: Fiscal inputs
A30: Average annual wage of retained cohort (€) | B30: 28000
A31: Effective tax + social contribution rate | B31: 0.35
A32: Annual public-service cost per added resident (€) | B32: 6000
A33: Annual national policy cost (€) | B33: 60000000
A34: Net annual fiscal benefit per retained contributor (€) | B34: =B30*B31-B32 -> 3800
A35: Approx. break-even retained contributors / year | B35: =IF(B33<=0,"n/a",B32/B33) -> 0.0001

Sheet Scenario_Drivers
A1: Scenario tuning parameters
A3: Scenario | B3: Inflow multiplier | C3: Retention multiplier | D3: Exit multiplier | E3: Parent LF multiplier | F3: Policy cost multiplier | G3: Pop decline adder | H3: Work decline adder | I3: Old-age growth adder
A4: Baseline | B4: 0 | C4: 1 | D4: 0 | E4: 0 | F4: 0 | G4: 0 | H4: 0 | I4: 0
A5: Moderate | B5: 1 | C5: 1 | D5: 1 | E5: 1 | F5: 1 | G5: 0 | H5: 0 | I5: 0
A6: Strong | B6: 1.35 | C6: 1.05 | D6: 0.9 | E6: 1.2 | F6: 1.1 | G6: 0 | H6: 0 | I6: 0
A7: Stress | B7: 0.55 | C7: 0.9 | D7: 1.15 | E7: 0.6 | F7: 0.9 | G7: 0.002 | H7: 0.0015 | I7: 0.0005
A10: Interpretation
A11: Baseline = official no-policy path. Moderate = reasonable implementation. Strong = stronger retention and lower leakage. Stress = weaker implementation plus slightly harsher background conditions.

Sheet Model
A1: Scenario projections, 2025–2050
A3: Year | B3: Base_Pop | C3: Base_Work | D3: Base_Old | E3: Base_Dep | F3: Base_NetRet | G3: Base_Fiscal | H3: Mod_Pop | I3: Mod_Work | J3: Mod_Old | K3: Mod_Dep | L3: Mod_NetRet | M3: Mod_Fiscal | N3: Strong_Pop | O3: Strong_Work | P3: Strong_Old | Q3: Strong_Dep | R3: Strong_NetRet | S3: Strong_Fiscal | T3: Stress_Pop | U3: Stress_Work | V3: Stress_Old | W3: Stress_Dep | X3: Stress_NetRet | Y3: Stress_Fiscal
A4: 2025 | B4: =Inputs!B9 -> 2890000 | C4: =Inputs!B10 -> 1750000 | D4: =Inputs!B11 -> 560000 | E4: =IFERROR(D4/C4,0) -> 0.32 | F4: 0 | G4: =F4*Inputs!B33-Inputs!B32*Scenario_Drivers!F4 -> 0 | H4: =Inputs!B9 -> 2890000 | I4: =Inputs!B10 -> 1750000 | J4: =Inputs!B11 -> 560000 | K4: =IFERROR(J4/I4,0) -> 0.32 | L4: =((Inputs!B21+Inputs!B22+Inputs!B23)*Scenario_Drivers!B5)*(Inputs!B24*Scenario_Drivers!C5)-(Inputs!B25*Scenario_Drivers!D5) -> 2770 | M4: =L4*Inputs!B33 + Inputs!B26*Scenario_Drivers!E5*(Inputs!B30*Inputs!B31) - Inputs!B32*Scenario_Drivers!F5 -> 166204404000 | N4: =Inputs!B9 -> 2890000 | O4: =Inputs!B10 -> 1750000 | P4: =Inputs!B11 -> 560000 | Q4: =IFERROR(P4/O4,0) -> 0.32 | R4: =((Inputs!B21+Inputs!B22+Inputs!B23)*Scenario_Drivers!B6)*(Inputs!B24*Scenario_Drivers!C6)-(Inputs!B25*Scenario_Drivers!D6) -> 4340.475 | S4: =R4*Inputs!B33 + Inputs!B26*Scenario_Drivers!E6*(Inputs!B30*Inputs!B31) - Inputs!B32*Scenario_Drivers!F6 -> 260433785400 | T4: =Inputs!B9 -> 2890000 | U4: =Inputs!B10 -> 1750000 | V4: =Inputs!B11 -> 560000 | W4: =IFERROR(V4/U4,0) -> 0.32 | X4: =((Inputs!B21+Inputs!B22+Inputs!B23)*Scenario_Drivers!B7)*(Inputs!B24*Scenario_Drivers!C7)-(Inputs!B25*Scenario_Drivers!D7) -> 847.15 | Y4: =X4*Inputs!B33 + Inputs!B26*Scenario_Drivers!E7*(Inputs!B30*Inputs!B31) - Inputs!B32*Scenario_Drivers!F7 -> 50831640600
A5: 2026 | B5: =B4*(1-(Inputs!B12+Scenario_Drivers!G4)) -> 2865158.9 | C5: =C4*(1-(Inputs!B13+Scenario_Drivers!H4)) -> 1728108.3 | D5: =D4*(1+(Inputs!B14+Scenario_Drivers!I4)) -> 566247.48 | E5: =IFERROR(D5/C5,0) -> 0.32766897 | F5: 0 | G5: =F5*Inputs!B33-Inputs!B32*Scenario_Drivers!F4 -> 0 | H5: =H4*(1-(Inputs!B12+Scenario_Drivers!G5))+L5 -> 2867928.9 | I5: =I4*(1-(Inputs!B13+Scenario_Drivers!H5))+L5+Inputs!B26*Scenario_Drivers!E5 -> 1731328.3 | J5: =J4*(1+(Inputs!B14+Scenario_Drivers!I5)) -> 566247.48 | K5: =IFERROR(J5/I5,0) -> 0.32705956 | L5: =((Inputs!B21+Inputs!B22+Inputs!B23)*Scenario_Drivers!B5)*(Inputs!B24*Scenario_Drivers!C5)-(Inputs!B25*Scenario_Drivers!D5) -> 2770 | M5: =L5*Inputs!B33 + Inputs!B26*Scenario_Drivers!E5*(Inputs!B30*Inputs!B31) - Inputs!B32*Scenario_Drivers!F5 -> 166204404000 | N5: =N4*(1-(Inputs!B12+Scenario_Drivers!G6))+R5 -> 2869499.3 | O5: =O4*(1-(Inputs!B13+Scenario_Drivers!H6))+R5+Inputs!B26*Scenario_Drivers!E6 -> 1732988.8 | P5: =P4*(1+(Inputs!B14+Scenario_Drivers!I6)) -> 566247.48 | Q5: =IFERROR(P5/O5,0) -> 0.32674619 | R5: =((Inputs!B21+Inputs!B22+Inputs!B23)*Scenario_Drivers!B6)*(Inputs!B24*Scenario_Drivers!C6)-(Inputs!B25*Scenario_Drivers!D6) -> 4340.475 | S5: =R5*Inputs!B33 + Inputs!B26*Scenario_Drivers!E6*(Inputs!B30*Inputs!B31) - Inputs!B32*Scenario_Drivers!F6 -> 260433785400 | T5: =T4*(1-(Inputs!B12+Scenario_Drivers!G7))+X5 -> 2860226 | U5: =U4*(1-(Inputs!B13+Scenario_Drivers!H7))+X5+Inputs!B26*Scenario_Drivers!E7 -> 1726600.5 | V5: =V4*(1+(Inputs!B14+Scenario_Drivers!I7)) -> 566527.48 | W5: =IFERROR(V5/U5,0) -> 0.3281173 | X5: =((Inputs!B21+Inputs!B22+Inputs!B23)*Scenario_Drivers!B7)*(Inputs!B24*Scenario_Drivers!C7)-(Inputs!B25*Scenario_Drivers!D7) -> 847.15 | Y5: =X5*Inputs!B33 + Inputs!B26*Scenario_Drivers!E7*(Inputs!B30*Inputs!B31) - Inputs!B32*Scenario_Drivers!F7 -> 50831640600
A6: 2027 | B6: =B5*(1-(Inputs!B12+Scenario_Drivers!G4)) -> 2840531.3 | C6: =C5*(1-(Inputs!B13+Scenario_Drivers!H4)) -> 1706490.5 | D6: =D5*(1+(Inputs!B14+Scenario_Drivers!I4)) -> 572564.66 | E6: =IFERROR(D6/C6,0) -> 0.33552174 | F6: 0 | G6: =F6*Inputs!B33-Inputs!B32*Scenario_Drivers!F4 -> 0 | H6: =H5*(1-(Inputs!B12+Scenario_Drivers!G5))+L6 -> 2846047.5 | I6: =I5*(1-(Inputs!B13+Scenario_Drivers!H5))+L6+Inputs!B26*Scenario_Drivers!E5 -> 1712890.2 | J6: =J5*(1+(Inputs!B14+Scenario_Drivers!I5)) -> 572564.66 | K6: =IFERROR(J6/I6,0) -> 0.33426816 | L6: =((Inputs!B21+Inputs!B22+Inputs!B23)*Scenario_Drivers!B5)*(Inputs!B24*Scenario_Drivers!C5)-(Inputs!B25*Scenario_Drivers!D5) -> 2770 | M6: =L6*Inputs!B33 + Inputs!B26*Scenario_Drivers!E5*(Inputs!B30*Inputs!B31) - Inputs!B32*Scenario_Drivers!F5 -> 166204404000 | N6: =N5*(1-(Inputs!B12+Scenario_Drivers!G6))+R6 -> 2849174.9 | O6: =O5*(1-(Inputs!B13+Scenario_Drivers!H6))+R6+Inputs!B26*Scenario_Drivers!E6 -> 1716190.4 | P6: =P5*(1+(Inputs!B14+Scenario_Drivers!I6)) -> 572564.66 | Q6: =IFERROR(P6/O6,0) -> 0.33362537 | R6: =((Inputs!B21+Inputs!B22+Inputs!B23)*Scenario_Drivers!B6)*(Inputs!B24*Scenario_Drivers!C6)-(Inputs!B25*Scenario_Drivers!D6) -> 4340.475 | S6: =R6*Inputs!B33 + Inputs!B26*Scenario_Drivers!E6*(Inputs!B30*Inputs!B31) - Inputs!B32*Scenario_Drivers!F6 -> 260433785400 | T6: =T5*(1-(Inputs!B12+Scenario_Drivers!G7))+X6 -> 2830767.5 | U6: =U5*(1-(Inputs!B13+Scenario_Drivers!H7))+X6+Inputs!B26*Scenario_Drivers!E7 -> 1703528.8 | V6: =V5*(1+(Inputs!B14+Scenario_Drivers!I7)) -> 573131.05 | W6: =IFERROR(V6/U6,0) -> 0.33643755 | X6: =((Inputs!B21+Inputs!B22+Inputs!B23)*Scenario_Drivers!B7)*(Inputs!B24*Scenario_Drivers!C7)-(Inputs!B25*Scenario_Drivers!D7) -> 847.15 | Y6: =X6*Inputs!B33 + Inputs!B26*Scenario_Drivers!E7*(Inputs!B30*Inputs!B31) - Inputs!B32*Scenario_Drivers!F7 -> 50831640600
A7: 2028 | B7: =B6*(1-(Inputs!B12+Scenario_Drivers!G4)) -> 2816115.4 | C7: =C6*(1-(Inputs!B13+Scenario_Drivers!H4)) -> 1685143.1 | D7: =D6*(1+(Inputs!B14+Scenario_Drivers!I4)) -> 578952.32 | E7: =IFERROR(D7/C7,0) -> 0.3435627 | F7: 0 | G7: =F7*Inputs!B33-Inputs!B32*Scenario_Drivers!F4 -> 0 | H7: =H6*(1-(Inputs!B12+Scenario_Drivers!G5))+L7 -> 2824354.1 | I7: =I6*(1-(Inputs!B13+Scenario_Drivers!H5))+L7+Inputs!B26*Scenario_Drivers!E5 -> 1694682.8 | J7: =J6*(1+(Inputs!B14+Scenario_Drivers!I5)) -> 578952.32 | K7: =IFERROR(J7/I7,0) -> 0.34162872 | L7: =((Inputs!B21+Inputs!B22+Inputs!B23)*Scenario_Drivers!B5)*(Inputs!B24*Scenario_Drivers!C5)-(Inputs!B25*Scenario_Drivers!D5) -> 2770 | M7: =L7*Inputs!B33 + Inputs!B26*Scenario_Drivers!E5*(Inputs!B30*Inputs!B31) - Inputs!B32*Scenario_Drivers!F5 -> 166204404000 | N7: =N6*(1-(Inputs!B12+Scenario_Drivers!G6))+R7 -> 2829025.2 | O7: =O6*(1-(Inputs!B13+Scenario_Drivers!H6))+R7+Inputs!B26*Scenario_Drivers!E6 -> 1699602.2 | P7: =P6*(1+(Inputs!B14+Scenario_Drivers!I6)) -> 578952.32 | Q7: =IFERROR(P7/O7,0) -> 0.34063991 | R7: =((Inputs!B21+Inputs!B22+Inputs!B23)*Scenario_Drivers!B6)*(Inputs!B24*Scenario_Drivers!C6)-(Inputs!B25*Scenario_Drivers!D6) -> 4340.475 | S7: =R7*Inputs!B33 + Inputs!B26*Scenario_Drivers!E6*(Inputs!B30*Inputs!B31) - Inputs!B32*Scenario_Drivers!F6 -> 260433785400 | T7: =T6*(1-(Inputs!B12+Scenario_Drivers!G7))+X7 -> 2801621.1 | U7: =U6*(1-(Inputs!B13+Scenario_Drivers!H7))+X7+Inputs!B26*Scenario_Drivers!E7 -> 1680780.3 | V7: =V6*(1+(Inputs!B14+Scenario_Drivers!I7)) -> 579811.59 | W7: =IFERROR(V7/U7,0) -> 0.34496572 | X7: =((Inputs!B21+Inputs!B22+Inputs!B23)*Scenario_Drivers!B7)*(Inputs!B24*Scenario_Drivers!C7)-(Inputs!B25*Scenario_Drivers!D7) -> 847.15 | Y7: =X7*Inputs!B33 + Inputs!B26*Scenario_Drivers!E7*(Inputs!B30*Inputs!B31) - Inputs!B32*Scenario_Drivers!F7 -> 50831640600
A8: 2029 | B8: =B7*(1-(Inputs!B12+Scenario_Drivers!G4)) -> 2791909.3 | C8: =C7*(1-(Inputs!B13+Scenario_Drivers!H4)) -> 1664062.8 | D8: =D7*(1+(Inputs!B14+Scenario_Drivers!I4)) -> 585411.23 | E8: =IFERROR(D8/C8,0) -> 0.35179636 | F8: 0 | G8: =F8*Inputs!B33-Inputs!B32*Scenario_Drivers!F4 -> 0 | H8: =H7*(1-(Inputs!B12+Scenario_Drivers!G5))+L8 -> 2802847.3 | I8: =I7*(1-(Inputs!B13+Scenario_Drivers!H5))+L8+Inputs!B26*Scenario_Drivers!E5 -> 1676703.1 | J8: =J7*(1+(Inputs!B14+Scenario_Drivers!I5)) -> 585411.23 | K8: =IFERROR(J8/I8,0) -> 0.34914424 | L8: =((Inputs!B21+Inputs!B22+Inputs!B23)*Scenario_Drivers!B5)*(Inputs!B24*Scenario_Drivers!C5)-(Inputs!B25*Scenario_Drivers!D5) -> 2770 | M8: =L8*Inputs!B33 + Inputs!B26*Scenario_Drivers!E5*(Inputs!B30*Inputs!B31) - Inputs!B32*Scenario_Drivers!F5 -> 166204404000 | N8: =N7*(1-(Inputs!B12+Scenario_Drivers!G6))+R8 -> 2809048.6 | O8: =O7*(1-(Inputs!B13+Scenario_Drivers!H6))+R8+Inputs!B26*Scenario_Drivers!E6 -> 1683221.4 | P8: =P7*(1+(Inputs!B14+Scenario_Drivers!I6)) -> 585411.23 | Q8: =IFERROR(P8/O8,0) -> 0.34779217 | R8: =((Inputs!B21+Inputs!B22+Inputs!B23)*Scenario_Drivers!B6)*(Inputs!B24*Scenario_Drivers!C6)-(Inputs!B25*Scenario_Drivers!D6) -> 4340.475 | S8: =R8*Inputs!B33 + Inputs!B26*Scenario_Drivers!E6*(Inputs!B30*Inputs!B31) - Inputs!B32*Scenario_Drivers!F6 -> 260433785400 | T8: =T7*(1-(Inputs!B12+Scenario_Drivers!G7))+X8 -> 2772783.6 | U8: =U7*(1-(Inputs!B13+Scenario_Drivers!H7))+X8+Inputs!B26*Scenario_Drivers!E7 -> 1658350.5 | V8: =V7*(1+(Inputs!B14+Scenario_Drivers!I7)) -> 586570 | W8: =IFERROR(V8/U8,0) -> 0.35370689 | X8: =((Inputs!B21+Inputs!B22+Inputs!B23)*Scenario_Drivers!B7)*(Inputs!B24*Scenario_Drivers!C7)-(Inputs!B25*Scenario_Drivers!D7) -> 847.15 | Y8: =X8*Inputs!B33 + Inputs!B26*Scenario_Drivers!E7*(Inputs!B30*Inputs!B31) - Inputs!B32*Scenario_Drivers!F7 -> 50831640600
A9: 2030 | B9: =B8*(1-(Inputs!B12+Scenario_Drivers!G4)) -> 2767911.3 | C9: =C8*(1-(Inputs!B13+Scenario_Drivers!H4)) -> 1643246.1 | D9: =D8*(1+(Inputs!B14+Scenario_Drivers!I4)) -> 591942.21 | E9: =IFERROR(D9/C9,0) -> 0.36022735 | F9: 0 | G9: =F9*Inputs!B33-Inputs!B32*Scenario_Drivers!F4 -> 0 | H9: =H8*(1-(Inputs!B12+Scenario_Drivers!G5))+L9 -> 2781525.3 | I9: =I8*(1-(Inputs!B13+Scenario_Drivers!H5))+L9+Inputs!B26*Scenario_Drivers!E5 -> 1658948.3 | J9: =J8*(1+(Inputs!B14+Scenario_Drivers!I5)) -> 591942.21 | K9: =IFERROR(J9/I9,0) -> 0.35681775 | L9: =((Inputs!B21+Inputs!B22+Inputs!B23)*Scenario_Drivers!B5)*(Inputs!B24*Scenario_Drivers!C5)-(Inputs!B25*Scenario_Drivers!D5) -> 2770 | M9: =L9*Inputs!B33 + Inputs!B26*Scenario_Drivers!E5*(Inputs!B30*Inputs!B31) - Inputs!B32*Scenario_Drivers!F5 -> 166204404000 | N9: =N8*(1-(Inputs!B12+Scenario_Drivers!G6))+R9 -> 2789243.8 | O9: =O8*(1-(Inputs!B13+Scenario_Drivers!H6))+R9+Inputs!B26*Scenario_Drivers!E6 -> 1667045.6 | P9: =P8*(1+(Inputs!B14+Scenario_Drivers!I6)) -> 591942.21 | Q9: =IFERROR(P9/O9,0) -> 0.3550846 | R9: =((Inputs!B21+Inputs!B22+Inputs!B23)*Scenario_Drivers!B6)*(Inputs!B24*Scenario_Drivers!C6)-(Inputs!B25*Scenario_Drivers!D6) -> 4340.475 | S9: =R9*Inputs!B33 + Inputs!B26*Scenario_Drivers!E6*(Inputs!B30*Inputs!B31) - Inputs!B32*Scenario_Drivers!F6 -> 260433785400 | T9: =T8*(1-(Inputs!B12+Scenario_Drivers!G7))+X9 -> 2744251.6 | U9: =U8*(1-(Inputs!B13+Scenario_Drivers!H7))+X9+Inputs!B26*Scenario_Drivers!E7 -> 1636234.9 | V9: =V8*(1+(Inputs!B14+Scenario_Drivers!I7)) -> 593407.19 | W9: =IFERROR(V9/U9,0) -> 0.36266625 | X9: =((Inputs!B21+Inputs!B22+Inputs!B23)*Scenario_Drivers!B7)*(Inputs!B24*Scenario_Drivers!C7)-(Inputs!B25*Scenario_Drivers!D7) -> 847.15 | Y9: =X9*Inputs!B33 + Inputs!B26*Scenario_Drivers!E7*(Inputs!B30*Inputs!B31) - Inputs!B32*Scenario_Drivers!F7 -> 50831640600
A10: 2031 | B10: =B9*(1-(Inputs!B12+Scenario_Drivers!G4)) -> 2744119.6 | C10: =C9*(1-(Inputs!B13+Scenario_Drivers!H4)) -> 1622689.9 | D10: =D9*(1+(Inputs!B14+Scenario_Drivers!I4)) -> 598546.05 | E10: =IFERROR(D10/C10,0) -> 0.3688604 | F10: 0 | G10: =F10*Inputs!B33-Inputs!B32*Scenario_Drivers!F4 -> 0 | H10: =H9*(1-(Inputs!B12+Scenario_Drivers!G5))+L10 -> 2760386.5 | I10: =I9*(1-(Inputs!B13+Scenario_Drivers!H5))+L10+Inputs!B26*Scenario_Drivers!E5 -> 1641415.7 | J10: =J9*(1+(Inputs!B14+Scenario_Drivers!I5)) -> 598546.05 | K10: =IFERROR(J10/I10,0) -> 0.36465233 | L10: =((Inputs!B21+Inputs!B22+Inputs!B23)*Scenario_Drivers!B5)*(Inputs!B24*Scenario_Drivers!C5)-(Inputs!B25*Scenario_Drivers!D5) -> 2770 | M10: =L10*Inputs!B33 + Inputs!B26*Scenario_Drivers!E5*(Inputs!B30*Inputs!B31) - Inputs!B32*Scenario_Drivers!F5 -> 166204404000 | N10: =N9*(1-(Inputs!B12+Scenario_Drivers!G6))+R10 -> 2769609.2 | O10: =O9*(1-(Inputs!B13+Scenario_Drivers!H6))+R10+Inputs!B26*Scenario_Drivers!E6 -> 1651072.1 | P10: =P9*(1+(Inputs!B14+Scenario_Drivers!I6)) -> 598546.05 | Q10: =IFERROR(P10/O10,0) -> 0.36251963 | R10: =((Inputs!B21+Inputs!B22+Inputs!B23)*Scenario_Drivers!B6)*(Inputs!B24*Scenario_Drivers!C6)-(Inputs!B25*Scenario_Drivers!D6) -> 4340.475 | S10: =R10*Inputs!B33 + Inputs!B26*Scenario_Drivers!E6*(Inputs!B30*Inputs!B31) - Inputs!B32*Scenario_Drivers!F6 -> 260433785400 | T10: =T9*(1-(Inputs!B12+Scenario_Drivers!G7))+X10 -> 2716021.9 | U10: =U9*(1-(Inputs!B13+Scenario_Drivers!H7))+X10+Inputs!B26*Scenario_Drivers!E7 -> 1614429.2 | V10: =V9*(1+(Inputs!B14+Scenario_Drivers!I7)) -> 600324.07 | W10: =IFERROR(V10/U10,0) -> 0.37184911 | X10: =((Inputs!B21+Inputs!B22+Inputs!B23)*Scenario_Drivers!B7)*(Inputs!B24*Scenario_Drivers!C7)-(Inputs!B25*Scenario_Drivers!D7) -> 847.15 | Y10: =X10*Inputs!B33 + Inputs!B26*Scenario_Drivers!E7*(Inputs!B30*Inputs!B31) - Inputs!B32*Scenario_Drivers!F7 -> 50831640600
A11: 2032 | B11: =B10*(1-(Inputs!B12+Scenario_Drivers!G4)) -> 2720532.4 | C11: =C10*(1-(Inputs!B13+Scenario_Drivers!H4)) -> 1602390.8 | D11: =D10*(1+(Inputs!B14+Scenario_Drivers!I4)) -> 605223.56 | E11: =IFERROR(D11/C11,0) -> 0.37770034 | F11: 0 | G11: =F11*Inputs!B33-Inputs!B32*Scenario_Drivers!F4 -> 0 | H11: =H10*(1-(Inputs!B12+Scenario_Drivers!G5))+L11 -> 2739429.5 | I11: =I10*(1-(Inputs!B13+Scenario_Drivers!H5))+L11+Inputs!B26*Scenario_Drivers!E5 -> 1624102.3 | J11: =J10*(1+(Inputs!B14+Scenario_Drivers!I5)) -> 605223.56 | K11: =IFERROR(J11/I11,0) -> 0.37265112 | L11: =((Inputs!B21+Inputs!B22+Inputs!B23)*Scenario_Drivers!B5)*(Inputs!B24*Scenario_Drivers!C5)-(Inputs!B25*Scenario_Drivers!D5) -> 2770 | M11: =L11*Inputs!B33 + Inputs!B26*Scenario_Drivers!E5*(Inputs!B30*Inputs!B31) - Inputs!B32*Scenario_Drivers!F5 -> 166204404000 | N11: =N10*(1-(Inputs!B12+Scenario_Drivers!G6))+R11 -> 2750143.4 | O11: =O10*(1-(Inputs!B13+Scenario_Drivers!H6))+R11+Inputs!B26*Scenario_Drivers!E6 -> 1635298.4 | P11: =P10*(1+(Inputs!B14+Scenario_Drivers!I6)) -> 605223.56 | Q11: =IFERROR(P11/O11,0) -> 0.37009976 | R11: =((Inputs!B21+Inputs!B22+Inputs!B23)*Scenario_Drivers!B6)*(Inputs!B24*Scenario_Drivers!C6)-(Inputs!B25*Scenario_Drivers!D6) -> 4340.475 | S11: =R11*Inputs!B33 + Inputs!B26*Scenario_Drivers!E6*(Inputs!B30*Inputs!B31) - Inputs!B32*Scenario_Drivers!F6 -> 260433785400 | T11: =T10*(1-(Inputs!B12+Scenario_Drivers!G7))+X11 -> 2688091.3 | U11: =U10*(1-(Inputs!B13+Scenario_Drivers!H7))+X11+Inputs!B26*Scenario_Drivers!E7 -> 1592929 | V11: =V10*(1+(Inputs!B14+Scenario_Drivers!I7)) -> 607321.58 | W11: =IFERROR(V11/U11,0) -> 0.38126093 | X11: =((Inputs!B21+Inputs!B22+Inputs!B23)*Scenario_Drivers!B7)*(Inputs!B24*Scenario_Drivers!C7)-(Inputs!B25*Scenario_Drivers!D7) -> 847.15 | Y11: =X11*Inputs!B33 + Inputs!B26*Scenario_Drivers!E7*(Inputs!B30*Inputs!B31) - Inputs!B32*Scenario_Drivers!F7 -> 50831640600
A12: 2033 | B12: =B11*(1-(Inputs!B12+Scenario_Drivers!G4)) -> 2697147.9 | C12: =C11*(1-(Inputs!B13+Scenario_Drivers!H4)) -> 1582345.7 | D12: =D11*(1+(Inputs!B14+Scenario_Drivers!I4)) -> 611975.56 | E12: =IFERROR(D12/C12,0) -> 0.38675213 | F12: 0 | G12: =F12*Inputs!B33-Inputs!B32*Scenario_Drivers!F4 -> 0 | H12: =H11*(1-(Inputs!B12+Scenario_Drivers!G5))+L12 -> 2718652.6 | I12: =I11*(1-(Inputs!B13+Scenario_Drivers!H5))+L12+Inputs!B26*Scenario_Drivers!E5 -> 1607005.6 | J12: =J11*(1+(Inputs!B14+Scenario_Drivers!I5)) -> 611975.56 | K12: =IFERROR(J12/I12,0) -> 0.38081732 | L12: =((Inputs!B21+Inputs!B22+Inputs!B23)*Scenario_Drivers!B5)*(Inputs!B24*Scenario_Drivers!C5)-(Inputs!B25*Scenario_Drivers!D5) -> 2770 | M12: =L12*Inputs!B33 + Inputs!B26*Scenario_Drivers!E5*(Inputs!B30*Inputs!B31) - Inputs!B32*Scenario_Drivers!F5 -> 166204404000 | N12: =N11*(1-(Inputs!B12+Scenario_Drivers!G6))+R12 -> 2730844.9 | O12: =O11*(1-(Inputs!B13+Scenario_Drivers!H6))+R12+Inputs!B26*Scenario_Drivers!E6 -> 1619722.1 | P12: =P11*(1+(Inputs!B14+Scenario_Drivers!I6)) -> 611975.56 | Q12: =IFERROR(P12/O12,0) -> 0.3778275 | R12: =((Inputs!B21+Inputs!B22+Inputs!B23)*Scenario_Drivers!B6)*(Inputs!B24*Scenario_Drivers!C6)-(Inputs!B25*Scenario_Drivers!D6) -> 4340.475 | S12: =R12*Inputs!B33 + Inputs!B26*Scenario_Drivers!E6*(Inputs!B30*Inputs!B31) - Inputs!B32*Scenario_Drivers!F6 -> 260433785400 | T12: =T11*(1-(Inputs!B12+Scenario_Drivers!G7))+X12 -> 2660456.7 | U12: =U11*(1-(Inputs!B13+Scenario_Drivers!H7))+X12+Inputs!B26*Scenario_Drivers!E7 -> 1571729.9 | V12: =V11*(1+(Inputs!B14+Scenario_Drivers!I7)) -> 614400.65 | W12: =IFERROR(V12/U12,0) -> 0.39090726 | X12: =((Inputs!B21+Inputs!B22+Inputs!B23)*Scenario_Drivers!B7)*(Inputs!B24*Scenario_Drivers!C7)-(Inputs!B25*Scenario_Drivers!D7) -> 847.15 | Y12: =X12*Inputs!B33 + Inputs!B26*Scenario_Drivers!E7*(Inputs!B30*Inputs!B31) - Inputs!B32*Scenario_Drivers!F7 -> 50831640600
A13: 2034 | B13: =B12*(1-(Inputs!B12+Scenario_Drivers!G4)) -> 2673964.5 | C13: =C12*(1-(Inputs!B13+Scenario_Drivers!H4)) -> 1562551.3 | D13: =D12*(1+(Inputs!B14+Scenario_Drivers!I4)) -> 618802.89 | E13: =IFERROR(D13/C13,0) -> 0.39602085 | F13: 0 | G13: =F13*Inputs!B33-Inputs!B32*Scenario_Drivers!F4 -> 0 | H13: =H12*(1-(Inputs!B12+Scenario_Drivers!G5))+L13 -> 2698054.3 | I13: =I12*(1-(Inputs!B13+Scenario_Drivers!H5))+L13+Inputs!B26*Scenario_Drivers!E5 -> 1590122.7 | J13: =J12*(1+(Inputs!B14+Scenario_Drivers!I5)) -> 618802.89 | K13: =IFERROR(J13/I13,0) -> 0.38915417 | L13: =((Inputs!B21+Inputs!B22+Inputs!B23)*Scenario_Drivers!B5)*(Inputs!B24*Scenario_Drivers!C5)-(Inputs!B25*Scenario_Drivers!D5) -> 2770 | M13: =L13*Inputs!B33 + Inputs!B26*Scenario_Drivers!E5*(Inputs!B30*Inputs!B31) - Inputs!B32*Scenario_Drivers!F5 -> 166204404000 | N13: =N12*(1-(Inputs!B12+Scenario_Drivers!G6))+R13 -> 2711712.2 | O13: =O12*(1-(Inputs!B13+Scenario_Drivers!H6))+R13+Inputs!B26*Scenario_Drivers!E6 -> 1604340.6 | P13: =P12*(1+(Inputs!B14+Scenario_Drivers!I6)) -> 618802.89 | Q13: =IFERROR(P13/O13,0) -> 0.38570543 | R13: =((Inputs!B21+Inputs!B22+Inputs!B23)*Scenario_Drivers!B6)*(Inputs!B24*Scenario_Drivers!C6)-(Inputs!B25*Scenario_Drivers!D6) -> 4340.475 | S13: =R13*Inputs!B33 + Inputs!B26*Scenario_Drivers!E6*(Inputs!B30*Inputs!B31) - Inputs!B32*Scenario_Drivers!F6 -> 260433785400 | T13: =T12*(1-(Inputs!B12+Scenario_Drivers!G7))+X13 -> 2633114.8 | U13: =U12*(1-(Inputs!B13+Scenario_Drivers!H7))+X13+Inputs!B26*Scenario_Drivers!E7 -> 1550827.9 | V13: =V12*(1+(Inputs!B14+Scenario_Drivers!I7)) -> 621562.24 | W13: =IFERROR(V13/U13,0) -> 0.40079382 | X13: =((Inputs!B21+Inputs!B22+Inputs!B23)*Scenario_Drivers!B7)*(Inputs!B24*Scenario_Drivers!C7)-(Inputs!B25*Scenario_Drivers!D7) -> 847.15 | Y13: =X13*Inputs!B33 + Inputs!B26*Scenario_Drivers!E7*(Inputs!B30*Inputs!B31) - Inputs!B32*Scenario_Drivers!F7 -> 50831640600
A14: 2035 | B14: =B13*(1-(Inputs!B12+Scenario_Drivers!G4)) -> 2650980.3 | C14: =C13*(1-(Inputs!B13+Scenario_Drivers!H4)) -> 1543004.5 | D14: =D13*(1+(Inputs!B14+Scenario_Drivers!I4)) -> 625706.39 | E14: =IFERROR(D14/C14,0) -> 0.40551171 | F14: 0 | G14: =F14*Inputs!B33-Inputs!B32*Scenario_Drivers!F4 -> 0 | H14: =H13*(1-(Inputs!B12+Scenario_Drivers!G5))+L14 -> 2677633.1 | I14: =I13*(1-(Inputs!B13+Scenario_Drivers!H5))+L14+Inputs!B26*Scenario_Drivers!E5 -> 1573451 | J14: =J13*(1+(Inputs!B14+Scenario_Drivers!I5)) -> 625706.39 | K14: =IFERROR(J14/I14,0) -> 0.39766499 | L14: =((Inputs!B21+Inputs!B22+Inputs!B23)*Scenario_Drivers!B5)*(Inputs!B24*Scenario_Drivers!C5)-(Inputs!B25*Scenario_Drivers!D5) -> 2770 | M14: =L14*Inputs!B33 + Inputs!B26*Scenario_Drivers!E5*(Inputs!B30*Inputs!B31) - Inputs!B32*Scenario_Drivers!F5 -> 166204404000 | N14: =N13*(1-(Inputs!B12+Scenario_Drivers!G6))+R14 -> 2692744.1 | O14: =O13*(1-(Inputs!B13+Scenario_Drivers!H6))+R14+Inputs!B26*Scenario_Drivers!E6 -> 1589151.6 | P14: =P13*(1+(Inputs!B14+Scenario_Drivers!I6)) -> 625706.39 | Q14: =IFERROR(P14/O14,0) -> 0.39373613 | R14: =((Inputs!B21+Inputs!B22+Inputs!B23)*Scenario_Drivers!B6)*(Inputs!B24*Scenario_Drivers!C6)-(Inputs!B25*Scenario_Drivers!D6) -> 4340.475 | S14: =R14*Inputs!B33 + Inputs!B26*Scenario_Drivers!E6*(Inputs!B30*Inputs!B31) - Inputs!B32*Scenario_Drivers!F6 -> 260433785400 | T14: =T13*(1-(Inputs!B12+Scenario_Drivers!G7))+X14 -> 2606062.7 | U14: =U13*(1-(Inputs!B13+Scenario_Drivers!H7))+X14+Inputs!B26*Scenario_Drivers!E7 -> 1530218.7 | V14: =V13*(1+(Inputs!B14+Scenario_Drivers!I7)) -> 628807.3 | W14: =IFERROR(V14/U14,0) -> 0.41092643 | X14: =((Inputs!B21+Inputs!B22+Inputs!B23)*Scenario_Drivers!B7)*(Inputs!B24*Scenario_Drivers!C7)-(Inputs!B25*Scenario_Drivers!D7) -> 847.15 | Y14: =X14*Inputs!B33 + Inputs!B26*Scenario_Drivers!E7*(Inputs!B30*Inputs!B31) - Inputs!B32*Scenario_Drivers!F7 -> 50831640600
A15: 2036 | B15: =B14*(1-(Inputs!B12+Scenario_Drivers!G4)) -> 2628193.7 | C15: =C14*(1-(Inputs!B13+Scenario_Drivers!H4)) -> 1523702.2 | D15: =D14*(1+(Inputs!B14+Scenario_Drivers!I4)) -> 632686.91 | E15: =IFERROR(D15/C15,0) -> 0.41523002 | F15: 0 | G15: =F15*Inputs!B33-Inputs!B32*Scenario_Drivers!F4 -> 0 | H15: =H14*(1-(Inputs!B12+Scenario_Drivers!G5))+L15 -> 2657387.3 | I15: =I14*(1-(Inputs!B13+Scenario_Drivers!H5))+L15+Inputs!B26*Scenario_Drivers!E5 -> 1556987.9 | J15: =J14*(1+(Inputs!B14+Scenario_Drivers!I5)) -> 632686.91 | K15: =IFERROR(J15/I15,0) -> 0.40635313 | L15: =((Inputs!B21+Inputs!B22+Inputs!B23)*Scenario_Drivers!B5)*(Inputs!B24*Scenario_Drivers!C5)-(Inputs!B25*Scenario_Drivers!D5) -> 2770 | M15: =L15*Inputs!B33 + Inputs!B26*Scenario_Drivers!E5*(Inputs!B30*Inputs!B31) - Inputs!B32*Scenario_Drivers!F5 -> 166204404000 | N15: =N14*(1-(Inputs!B12+Scenario_Drivers!G6))+R15 -> 2673938.9 | O15: =O14*(1-(Inputs!B13+Scenario_Drivers!H6))+R15+Inputs!B26*Scenario_Drivers!E6 -> 1574152.5 | P15: =P14*(1+(Inputs!B14+Scenario_Drivers!I6)) -> 632686.91 | Q15: =IFERROR(P15/O15,0) -> 0.40192225 | R15: =((Inputs!B21+Inputs!B22+Inputs!B23)*Scenario_Drivers!B6)*(Inputs!B24*Scenario_Drivers!C6)-(Inputs!B25*Scenario_Drivers!D6) -> 4340.475 | S15: =R15*Inputs!B33 + Inputs!B26*Scenario_Drivers!E6*(Inputs!B30*Inputs!B31) - Inputs!B32*Scenario_Drivers!F6 -> 260433785400 | T15: =T14*(1-(Inputs!B12+Scenario_Drivers!G7))+X15 -> 2579297.2 | U15: =U14*(1-(Inputs!B13+Scenario_Drivers!H7))+X15+Inputs!B26*Scenario_Drivers!E7 -> 1509898.2 | V15: =V14*(1+(Inputs!B14+Scenario_Drivers!I7)) -> 636136.81 | W15: =IFERROR(V15/U15,0) -> 0.42131106 | X15: =((Inputs!B21+Inputs!B22+Inputs!B23)*Scenario_Drivers!B7)*(Inputs!B24*Scenario_Drivers!C7)-(Inputs!B25*Scenario_Drivers!D7) -> 847.15 | Y15: =X15*Inputs!B33 + Inputs!B26*Scenario_Drivers!E7*(Inputs!B30*Inputs!B31) - Inputs!B32*Scenario_Drivers!F7 -> 50831640600
A16: 2037 | B16: =B15*(1-(Inputs!B12+Scenario_Drivers!G4)) -> 2605602.9 | C16: =C15*(1-(Inputs!B13+Scenario_Drivers!H4)) -> 1504641.4 | D16: =D15*(1+(Inputs!B14+Scenario_Drivers!I4)) -> 639745.3 | E16: =IFERROR(D16/C16,0) -> 0.42518123 | F16: 0 | G16: =F16*Inputs!B33-Inputs!B32*Scenario_Drivers!F4 -> 0 | H16: =H15*(1-(Inputs!B12+Scenario_Drivers!G5))+L16 -> 2637315.7 | I16: =I15*(1-(Inputs!B13+Scenario_Drivers!H5))+L16+Inputs!B26*Scenario_Drivers!E5 -> 1540730.7 | J16: =J15*(1+(Inputs!B14+Scenario_Drivers!I5)) -> 639745.3 | K16: =IFERROR(J16/I16,0) -> 0.41522201 | L16: =((Inputs!B21+Inputs!B22+Inputs!B23)*Scenario_Drivers!B5)*(Inputs!B24*Scenario_Drivers!C5)-(Inputs!B25*Scenario_Drivers!D5) -> 2770 | M16: =L16*Inputs!B33 + Inputs!B26*Scenario_Drivers!E5*(Inputs!B30*Inputs!B31) - Inputs!B32*Scenario_Drivers!F5 -> 166204404000 | N16: =N15*(1-(Inputs!B12+Scenario_Drivers!G6))+R16 -> 2655295.5 | O16: =O15*(1-(Inputs!B13+Scenario_Drivers!H6))+R16+Inputs!B26*Scenario_Drivers!E6 -> 1559341.1 | P16: =P15*(1+(Inputs!B14+Scenario_Drivers!I6)) -> 639745.3 | Q16: =IFERROR(P16/O16,0) -> 0.41026643 | R16: =((Inputs!B21+Inputs!B22+Inputs!B23)*Scenario_Drivers!B6)*(Inputs!B24*Scenario_Drivers!C6)-(Inputs!B25*Scenario_Drivers!D6) -> 4340.475 | S16: =R16*Inputs!B33 + Inputs!B26*Scenario_Drivers!E6*(Inputs!B30*Inputs!B31) - Inputs!B32*Scenario_Drivers!F6 -> 260433785400 | T16: =T15*(1-(Inputs!B12+Scenario_Drivers!G7))+X16 -> 2552815.3 | U16: =U15*(1-(Inputs!B13+Scenario_Drivers!H7))+X16+Inputs!B26*Scenario_Drivers!E7 -> 1489862.4 | V16: =V15*(1+(Inputs!B14+Scenario_Drivers!I7)) -> 643551.76 | W16: =IFERROR(V16/U16,0) -> 0.43195383 | X16: =((Inputs!B21+Inputs!B22+Inputs!B23)*Scenario_Drivers!B7)*(Inputs!B24*Scenario_Drivers!C7)-(Inputs!B25*Scenario_Drivers!D7) -> 847.15 | Y16: =X16*Inputs!B33 + Inputs!B26*Scenario_Drivers!E7*(Inputs!B30*Inputs!B31) - Inputs!B32*Scenario_Drivers!F7 -> 50831640600
A17: 2038 | B17: =B16*(1-(Inputs!B12+Scenario_Drivers!G4)) -> 2583206.3 | C17: =C16*(1-(Inputs!B13+Scenario_Drivers!H4)) -> 1485819.1 | D17: =D16*(1+(Inputs!B14+Scenario_Drivers!I4)) -> 646882.44 | E17: =IFERROR(D17/C17,0) -> 0.43537093 | F17: 0 | G17: =F17*Inputs!B33-Inputs!B32*Scenario_Drivers!F4 -> 0 | H17: =H16*(1-(Inputs!B12+Scenario_Drivers!G5))+L17 -> 2617416.5 | I17: =I16*(1-(Inputs!B13+Scenario_Drivers!H5))+L17+Inputs!B26*Scenario_Drivers!E5 -> 1524676.9 | J17: =J16*(1+(Inputs!B14+Scenario_Drivers!I5)) -> 646882.44 | K17: =IFERROR(J17/I17,0) -> 0.42427509 | L17: =((Inputs!B21+Inputs!B22+Inputs!B23)*Scenario_Drivers!B5)*(Inputs!B24*Scenario_Drivers!C5)-(Inputs!B25*Scenario_Drivers!D5) -> 2770 | M17: =L17*Inputs!B33 + Inputs!B26*Scenario_Drivers!E5*(Inputs!B30*Inputs!B31) - Inputs!B32*Scenario_Drivers!F5 -> 166204404000 | N17: =N16*(1-(Inputs!B12+Scenario_Drivers!G6))+R17 -> 2636812.2 | O17: =O16*(1-(Inputs!B13+Scenario_Drivers!H6))+R17+Inputs!B26*Scenario_Drivers!E6 -> 1544714.9 | P17: =P16*(1+(Inputs!B14+Scenario_Drivers!I6)) -> 646882.44 | Q17: =IFERROR(P17/O17,0) -> 0.4187714 | R17: =((Inputs!B21+Inputs!B22+Inputs!B23)*Scenario_Drivers!B6)*(Inputs!B24*Scenario_Drivers!C6)-(Inputs!B25*Scenario_Drivers!D6) -> 4340.475 | S17: =R17*Inputs!B33 + Inputs!B26*Scenario_Drivers!E6*(Inputs!B30*Inputs!B31) - Inputs!B32*Scenario_Drivers!F6 -> 260433785400 | T17: =T16*(1-(Inputs!B12+Scenario_Drivers!G7))+X17 -> 2526613.9 | U17: =U16*(1-(Inputs!B13+Scenario_Drivers!H7))+X17+Inputs!B26*Scenario_Drivers!E7 -> 1470107.3 | V17: =V16*(1+(Inputs!B14+Scenario_Drivers!I7)) -> 651053.14 | W17: =IFERROR(V17/U17,0) -> 0.44286098 | X17: =((Inputs!B21+Inputs!B22+Inputs!B23)*Scenario_Drivers!B7)*(Inputs!B24*Scenario_Drivers!C7)-(Inputs!B25*Scenario_Drivers!D7) -> 847.15 | Y17: =X17*Inputs!B33 + Inputs!B26*Scenario_Drivers!E7*(Inputs!B30*Inputs!B31) - Inputs!B32*Scenario_Drivers!F7 -> 50831640600
A18: 2039 | B18: =B17*(1-(Inputs!B12+Scenario_Drivers!G4)) -> 2561002.3 | C18: =C17*(1-(Inputs!B13+Scenario_Drivers!H4)) -> 1467232.2 | D18: =D17*(1+(Inputs!B14+Scenario_Drivers!I4)) -> 654099.2 | E18: =IFERROR(D18/C18,0) -> 0.44580483 | F18: 0 | G18: =F18*Inputs!B33-Inputs!B32*Scenario_Drivers!F4 -> 0 | H18: =H17*(1-(Inputs!B12+Scenario_Drivers!G5))+L18 -> 2597688.4 | I18: =I17*(1-(Inputs!B13+Scenario_Drivers!H5))+L18+Inputs!B26*Scenario_Drivers!E5 -> 1508823.9 | J18: =J17*(1+(Inputs!B14+Scenario_Drivers!I5)) -> 654099.2 | K18: =IFERROR(J18/I18,0) -> 0.43351593 | L18: =((Inputs!B21+Inputs!B22+Inputs!B23)*Scenario_Drivers!B5)*(Inputs!B24*Scenario_Drivers!C5)-(Inputs!B25*Scenario_Drivers!D5) -> 2770 | M18: =L18*Inputs!B33 + Inputs!B26*Scenario_Drivers!E5*(Inputs!B30*Inputs!B31) - Inputs!B32*Scenario_Drivers!F5 -> 166204404000 | N18: =N17*(1-(Inputs!B12+Scenario_Drivers!G6))+R18 -> 2618487.8 | O18: =O17*(1-(Inputs!B13+Scenario_Drivers!H6))+R18+Inputs!B26*Scenario_Drivers!E6 -> 1530271.8 | P18: =P17*(1+(Inputs!B14+Scenario_Drivers!I6)) -> 654099.2 | Q18: =IFERROR(P18/O18,0) -> 0.4274399 | R18: =((Inputs!B21+Inputs!B22+Inputs!B23)*Scenario_Drivers!B6)*(Inputs!B24*Scenario_Drivers!C6)-(Inputs!B25*Scenario_Drivers!D6) -> 4340.475 | S18: =R18*Inputs!B33 + Inputs!B26*Scenario_Drivers!E6*(Inputs!B30*Inputs!B31) - Inputs!B32*Scenario_Drivers!F6 -> 260433785400 | T18: =T17*(1-(Inputs!B12+Scenario_Drivers!G7))+X18 -> 2500690.2 | U18: =U17*(1-(Inputs!B13+Scenario_Drivers!H7))+X18+Inputs!B26*Scenario_Drivers!E7 -> 1450628.9 | V18: =V17*(1+(Inputs!B14+Scenario_Drivers!I7)) -> 658641.96 | W18: =IFERROR(V18/U18,0) -> 0.4540389 | X18: =((Inputs!B21+Inputs!B22+Inputs!B23)*Scenario_Drivers!B7)*(Inputs!B24*Scenario_Drivers!C7)-(Inputs!B25*Scenario_Drivers!D7) -> 847.15 | Y18: =X18*Inputs!B33 + Inputs!B26*Scenario_Drivers!E7*(Inputs!B30*Inputs!B31) - Inputs!B32*Scenario_Drivers!F7 -> 50831640600
A19: 2040 | B19: =B18*(1-(Inputs!B12+Scenario_Drivers!G4)) -> 2538989.1 | C19: =C18*(1-(Inputs!B13+Scenario_Drivers!H4)) -> 1448877.8 | D19: =D18*(1+(Inputs!B14+Scenario_Drivers!I4)) -> 661396.47 | E19: =IFERROR(D19/C19,0) -> 0.45648878 | F19: 0 | G19: =F19*Inputs!B33-Inputs!B32*Scenario_Drivers!F4 -> 0 | H19: =H18*(1-(Inputs!B12+Scenario_Drivers!G5))+L19 -> 2578129.8 | I19: =I18*(1-(Inputs!B13+Scenario_Drivers!H5))+L19+Inputs!B26*Scenario_Drivers!E5 -> 1493169.2 | J19: =J18*(1+(Inputs!B14+Scenario_Drivers!I5)) -> 661396.47 | K19: =IFERROR(J19/I19,0) -> 0.44294809 | L19: =((Inputs!B21+Inputs!B22+Inputs!B23)*Scenario_Drivers!B5)*(Inputs!B24*Scenario_Drivers!C5)-(Inputs!B25*Scenario_Drivers!D5) -> 2770 | M19: =L19*Inputs!B33 + Inputs!B26*Scenario_Drivers!E5*(Inputs!B30*Inputs!B31) - Inputs!B32*Scenario_Drivers!F5 -> 166204404000 | N19: =N18*(1-(Inputs!B12+Scenario_Drivers!G6))+R19 -> 2600321 | O19: =O18*(1-(Inputs!B13+Scenario_Drivers!H6))+R19+Inputs!B26*Scenario_Drivers!E6 -> 1516009.3 | P19: =P18*(1+(Inputs!B14+Scenario_Drivers!I6)) -> 661396.47 | Q19: =IFERROR(P19/O19,0) -> 0.43627469 | R19: =((Inputs!B21+Inputs!B22+Inputs!B23)*Scenario_Drivers!B6)*(Inputs!B24*Scenario_Drivers!C6)-(Inputs!B25*Scenario_Drivers!D6) -> 4340.475 | S19: =R19*Inputs!B33 + Inputs!B26*Scenario_Drivers!E6*(Inputs!B30*Inputs!B31) - Inputs!B32*Scenario_Drivers!F6 -> 260433785400 | T19: =T18*(1-(Inputs!B12+Scenario_Drivers!G7))+X19 -> 2475041.2 | U19: =U18*(1-(Inputs!B13+Scenario_Drivers!H7))+X19+Inputs!B26*Scenario_Drivers!E7 -> 1431423.4 | V19: =V18*(1+(Inputs!B14+Scenario_Drivers!I7)) -> 666319.23 | W19: =IFERROR(V19/U19,0) -> 0.46549415 | X19: =((Inputs!B21+Inputs!B22+Inputs!B23)*Scenario_Drivers!B7)*(Inputs!B24*Scenario_Drivers!C7)-(Inputs!B25*Scenario_Drivers!D7) -> 847.15 | Y19: =X19*Inputs!B33 + Inputs!B26*Scenario_Drivers!E7*(Inputs!B30*Inputs!B31) - Inputs!B32*Scenario_Drivers!F7 -> 50831640600
A20: 2041 | B20: =B19*(1-(Inputs!B12+Scenario_Drivers!G4)) -> 2517165.1 | C20: =C19*(1-(Inputs!B13+Scenario_Drivers!H4)) -> 1430753 | D20: =D19*(1+(Inputs!B14+Scenario_Drivers!I4)) -> 668775.15 | E20: =IFERROR(D20/C20,0) -> 0.46742878 | F20: 0 | G20: =F20*Inputs!B33-Inputs!B32*Scenario_Drivers!F4 -> 0 | H20: =H19*(1-(Inputs!B12+Scenario_Drivers!G5))+L20 -> 2558739.4 | I20: =I19*(1-(Inputs!B13+Scenario_Drivers!H5))+L20+Inputs!B26*Scenario_Drivers!E5 -> 1477710.4 | J20: =J19*(1+(Inputs!B14+Scenario_Drivers!I5)) -> 668775.15 | K20: =IFERROR(J20/I20,0) -> 0.45257525 | L20: =((Inputs!B21+Inputs!B22+Inputs!B23)*Scenario_Drivers!B5)*(Inputs!B24*Scenario_Drivers!C5)-(Inputs!B25*Scenario_Drivers!D5) -> 2770 | M20: =L20*Inputs!B33 + Inputs!B26*Scenario_Drivers!E5*(Inputs!B30*Inputs!B31) - Inputs!B32*Scenario_Drivers!F5 -> 166204404000 | N20: =N19*(1-(Inputs!B12+Scenario_Drivers!G6))+R20 -> 2582310.3 | O20: =O19*(1-(Inputs!B13+Scenario_Drivers!H6))+R20+Inputs!B26*Scenario_Drivers!E6 -> 1501925.2 | P20: =P19*(1+(Inputs!B14+Scenario_Drivers!I6)) -> 668775.15 | Q20: =IFERROR(P20/O20,0) -> 0.44527861 | R20: =((Inputs!B21+Inputs!B22+Inputs!B23)*Scenario_Drivers!B6)*(Inputs!B24*Scenario_Drivers!C6)-(Inputs!B25*Scenario_Drivers!D6) -> 4340.475 | S20: =R20*Inputs!B33 + Inputs!B26*Scenario_Drivers!E6*(Inputs!B30*Inputs!B31) - Inputs!B32*Scenario_Drivers!F6 -> 260433785400 | T20: =T19*(1-(Inputs!B12+Scenario_Drivers!G7))+X20 -> 2449664 | U20: =U19*(1-(Inputs!B13+Scenario_Drivers!H7))+X20+Inputs!B26*Scenario_Drivers!E7 -> 1412487 | V20: =V19*(1+(Inputs!B14+Scenario_Drivers!I7)) -> 674085.99 | W20: =IFERROR(V20/U20,0) -> 0.47723341 | X20: =((Inputs!B21+Inputs!B22+Inputs!B23)*Scenario_Drivers!B7)*(Inputs!B24*Scenario_Drivers!C7)-(Inputs!B25*Scenario_Drivers!D7) -> 847.15 | Y20: =X20*Inputs!B33 + Inputs!B26*Scenario_Drivers!E7*(Inputs!B30*Inputs!B31) - Inputs!B32*Scenario_Drivers!F7 -> 50831640600
A21: 2042 | B21: =B20*(1-(Inputs!B12+Scenario_Drivers!G4)) -> 2495528.7 | C21: =C20*(1-(Inputs!B13+Scenario_Drivers!H4)) -> 1412855 | D21: =D20*(1+(Inputs!B14+Scenario_Drivers!I4)) -> 676236.16 | E21: =IFERROR(D21/C21,0) -> 0.47863097 | F21: 0 | G21: =F21*Inputs!B33-Inputs!B32*Scenario_Drivers!F4 -> 0 | H21: =H20*(1-(Inputs!B12+Scenario_Drivers!G5))+L21 -> 2539515.6 | I21: =I20*(1-(Inputs!B13+Scenario_Drivers!H5))+L21+Inputs!B26*Scenario_Drivers!E5 -> 1462445 | J21: =J20*(1+(Inputs!B14+Scenario_Drivers!I5)) -> 676236.16 | K21: =IFERROR(J21/I21,0) -> 0.4624011 | L21: =((Inputs!B21+Inputs!B22+Inputs!B23)*Scenario_Drivers!B5)*(Inputs!B24*Scenario_Drivers!C5)-(Inputs!B25*Scenario_Drivers!D5) -> 2770 | M21: =L21*Inputs!B33 + Inputs!B26*Scenario_Drivers!E5*(Inputs!B30*Inputs!B31) - Inputs!B32*Scenario_Drivers!F5 -> 166204404000 | N21: =N20*(1-(Inputs!B12+Scenario_Drivers!G6))+R21 -> 2564454.4 | O21: =O20*(1-(Inputs!B13+Scenario_Drivers!H6))+R21+Inputs!B26*Scenario_Drivers!E6 -> 1488017.3 | P21: =P20*(1+(Inputs!B14+Scenario_Drivers!I6)) -> 676236.16 | Q21: =IFERROR(P21/O21,0) -> 0.45445451 | R21: =((Inputs!B21+Inputs!B22+Inputs!B23)*Scenario_Drivers!B6)*(Inputs!B24*Scenario_Drivers!C6)-(Inputs!B25*Scenario_Drivers!D6) -> 4340.475 | S21: =R21*Inputs!B33 + Inputs!B26*Scenario_Drivers!E6*(Inputs!B30*Inputs!B31) - Inputs!B32*Scenario_Drivers!F6 -> 260433785400 | T21: =T20*(1-(Inputs!B12+Scenario_Drivers!G7))+X21 -> 2424555.6 | U21: =U20*(1-(Inputs!B13+Scenario_Drivers!H7))+X21+Inputs!B26*Scenario_Drivers!E7 -> 1393815.9 | V21: =V20*(1+(Inputs!B14+Scenario_Drivers!I7)) -> 681943.29 | W21: =IFERROR(V21/U21,0) -> 0.48926353 | X21: =((Inputs!B21+Inputs!B22+Inputs!B23)*Scenario_Drivers!B7)*(Inputs!B24*Scenario_Drivers!C7)-(Inputs!B25*Scenario_Drivers!D7) -> 847.15 | Y21: =X21*Inputs!B33 + Inputs!B26*Scenario_Drivers!E7*(Inputs!B30*Inputs!B31) - Inputs!B32*Scenario_Drivers!F7 -> 50831640600
A22: 2043 | B22: =B21*(1-(Inputs!B12+Scenario_Drivers!G4)) -> 2474078.2 | C22: =C21*(1-(Inputs!B13+Scenario_Drivers!H4)) -> 1395180.9 | D22: =D21*(1+(Inputs!B14+Scenario_Drivers!I4)) -> 683780.39 | E22: =IFERROR(D22/C22,0) -> 0.49010162 | F22: 0 | G22: =F22*Inputs!B33-Inputs!B32*Scenario_Drivers!F4 -> 0 | H22: =H21*(1-(Inputs!B12+Scenario_Drivers!G5))+L22 -> 2520457.1 | I22: =I21*(1-(Inputs!B13+Scenario_Drivers!H5))+L22+Inputs!B26*Scenario_Drivers!E5 -> 1447370.5 | J22: =J21*(1+(Inputs!B14+Scenario_Drivers!I5)) -> 683780.39 | K22: =IFERROR(J22/I22,0) -> 0.47242943 | L22: =((Inputs!B21+Inputs!B22+Inputs!B23)*Scenario_Drivers!B5)*(Inputs!B24*Scenario_Drivers!C5)-(Inputs!B25*Scenario_Drivers!D5) -> 2770 | M22: =L22*Inputs!B33 + Inputs!B26*Scenario_Drivers!E5*(Inputs!B30*Inputs!B31) - Inputs!B32*Scenario_Drivers!F5 -> 166204404000 | N22: =N21*(1-(Inputs!B12+Scenario_Drivers!G6))+R22 -> 2546752 | O22: =O21*(1-(Inputs!B13+Scenario_Drivers!H6))+R22+Inputs!B26*Scenario_Drivers!E6 -> 1474283.4 | P22: =P21*(1+(Inputs!B14+Scenario_Drivers!I6)) -> 683780.39 | Q22: =IFERROR(P22/O22,0) -> 0.46380527 | R22: =((Inputs!B21+Inputs!B22+Inputs!B23)*Scenario_Drivers!B6)*(Inputs!B24*Scenario_Drivers!C6)-(Inputs!B25*Scenario_Drivers!D6) -> 4340.475 | S22: =R22*Inputs!B33 + Inputs!B26*Scenario_Drivers!E6*(Inputs!B30*Inputs!B31) - Inputs!B32*Scenario_Drivers!F6 -> 260433785400 | T22: =T21*(1-(Inputs!B12+Scenario_Drivers!G7))+X22 -> 2399713.2 | U22: =U21*(1-(Inputs!B13+Scenario_Drivers!H7))+X22+Inputs!B26*Scenario_Drivers!E7 -> 1375406.3 | V22: =V21*(1+(Inputs!B14+Scenario_Drivers!I7)) -> 689892.17 | W22: =IFERROR(V22/U22,0) -> 0.50159152 | X22: =((Inputs!B21+Inputs!B22+Inputs!B23)*Scenario_Drivers!B7)*(Inputs!B24*Scenario_Drivers!C7)-(Inputs!B25*Scenario_Drivers!D7) -> 847.15 | Y22: =X22*Inputs!B33 + Inputs!B26*Scenario_Drivers!E7*(Inputs!B30*Inputs!B31) - Inputs!B32*Scenario_Drivers!F7 -> 50831640600
A23: 2044 | B23: =B22*(1-(Inputs!B12+Scenario_Drivers!G4)) -> 2452812.2 | C23: =C22*(1-(Inputs!B13+Scenario_Drivers!H4)) -> 1377727.8 | D23: =D22*(1+(Inputs!B14+Scenario_Drivers!I4)) -> 691408.8 | E23: =IFERROR(D23/C23,0) -> 0.50184717 | F23: 0 | G23: =F23*Inputs!B33-Inputs!B32*Scenario_Drivers!F4 -> 0 | H23: =H22*(1-(Inputs!B12+Scenario_Drivers!G5))+L23 -> 2501562.4 | I23: =I22*(1-(Inputs!B13+Scenario_Drivers!H5))+L23+Inputs!B26*Scenario_Drivers!E5 -> 1432484.5 | J23: =J22*(1+(Inputs!B14+Scenario_Drivers!I5)) -> 691408.8 | K23: =IFERROR(J23/I23,0) -> 0.48266405 | L23: =((Inputs!B21+Inputs!B22+Inputs!B23)*Scenario_Drivers!B5)*(Inputs!B24*Scenario_Drivers!C5)-(Inputs!B25*Scenario_Drivers!D5) -> 2770 | M23: =L23*Inputs!B33 + Inputs!B26*Scenario_Drivers!E5*(Inputs!B30*Inputs!B31) - Inputs!B32*Scenario_Drivers!F5 -> 166204404000 | N23: =N22*(1-(Inputs!B12+Scenario_Drivers!G6))+R23 -> 2529201.7 | O23: =O22*(1-(Inputs!B13+Scenario_Drivers!H6))+R23+Inputs!B26*Scenario_Drivers!E6 -> 1460721.2 | P23: =P22*(1+(Inputs!B14+Scenario_Drivers!I6)) -> 691408.8 | Q23: =IFERROR(P23/O23,0) -> 0.47333384 | R23: =((Inputs!B21+Inputs!B22+Inputs!B23)*Scenario_Drivers!B6)*(Inputs!B24*Scenario_Drivers!C6)-(Inputs!B25*Scenario_Drivers!D6) -> 4340.475 | S23: =R23*Inputs!B33 + Inputs!B26*Scenario_Drivers!E6*(Inputs!B30*Inputs!B31) - Inputs!B32*Scenario_Drivers!F6 -> 260433785400 | T23: =T22*(1-(Inputs!B12+Scenario_Drivers!G7))+X23 -> 2375134.1 | U23: =U22*(1-(Inputs!B13+Scenario_Drivers!H7))+X23+Inputs!B26*Scenario_Drivers!E7 -> 1357254.7 | V23: =V22*(1+(Inputs!B14+Scenario_Drivers!I7)) -> 697933.7 | W23: =IFERROR(V23/U23,0) -> 0.51422456 | X23: =((Inputs!B21+Inputs!B22+Inputs!B23)*Scenario_Drivers!B7)*(Inputs!B24*Scenario_Drivers!C7)-(Inputs!B25*Scenario_Drivers!D7) -> 847.15 | Y23: =X23*Inputs!B33 + Inputs!B26*Scenario_Drivers!E7*(Inputs!B30*Inputs!B31) - Inputs!B32*Scenario_Drivers!F7 -> 50831640600
A24: 2045 | B24: =B23*(1-(Inputs!B12+Scenario_Drivers!G4)) -> 2431728.9 | C24: =C23*(1-(Inputs!B13+Scenario_Drivers!H4)) -> 1360493.1 | D24: =D23*(1+(Inputs!B14+Scenario_Drivers!I4)) -> 699122.3 | E24: =IFERROR(D24/C24,0) -> 0.51387421 | F24: 0 | G24: =F24*Inputs!B33-Inputs!B32*Scenario_Drivers!F4 -> 0 | H24: =H23*(1-(Inputs!B12+Scenario_Drivers!G5))+L24 -> 2482830.1 | I24: =I23*(1-(Inputs!B13+Scenario_Drivers!H5))+L24+Inputs!B26*Scenario_Drivers!E5 -> 1417784.8 | J24: =J23*(1+(Inputs!B14+Scenario_Drivers!I5)) -> 699122.3 | K24: =IFERROR(J24/I24,0) -> 0.49310889 | L24: =((Inputs!B21+Inputs!B22+Inputs!B23)*Scenario_Drivers!B5)*(Inputs!B24*Scenario_Drivers!C5)-(Inputs!B25*Scenario_Drivers!D5) -> 2770 | M24: =L24*Inputs!B33 + Inputs!B26*Scenario_Drivers!E5*(Inputs!B30*Inputs!B31) - Inputs!B32*Scenario_Drivers!F5 -> 166204404000 | N24: =N23*(1-(Inputs!B12+Scenario_Drivers!G6))+R24 -> 2511802.3 | O24: =O23*(1-(Inputs!B13+Scenario_Drivers!H6))+R24+Inputs!B26*Scenario_Drivers!E6 -> 1447328.8 | P24: =P23*(1+(Inputs!B14+Scenario_Drivers!I6)) -> 699122.3 | Q24: =IFERROR(P24/O24,0) -> 0.48304318 | R24: =((Inputs!B21+Inputs!B22+Inputs!B23)*Scenario_Drivers!B6)*(Inputs!B24*Scenario_Drivers!C6)-(Inputs!B25*Scenario_Drivers!D6) -> 4340.475 | S24: =R24*Inputs!B33 + Inputs!B26*Scenario_Drivers!E6*(Inputs!B30*Inputs!B31) - Inputs!B32*Scenario_Drivers!F6 -> 260433785400 | T24: =T23*(1-(Inputs!B12+Scenario_Drivers!G7))+X24 -> 2350815.4 | U24: =U23*(1-(Inputs!B13+Scenario_Drivers!H7))+X24+Inputs!B26*Scenario_Drivers!E7 -> 1339357.4 | V24: =V23*(1+(Inputs!B14+Scenario_Drivers!I7)) -> 706068.97 | W24: =IFERROR(V24/U24,0) -> 0.52716996 | X24: =((Inputs!B21+Inputs!B22+Inputs!B23)*Scenario_Drivers!B7)*(Inputs!B24*Scenario_Drivers!C7)-(Inputs!B25*Scenario_Drivers!D7) -> 847.15 | Y24: =X24*Inputs!B33 + Inputs!B26*Scenario_Drivers!E7*(Inputs!B30*Inputs!B31) - Inputs!B32*Scenario_Drivers!F7 -> 50831640600
A25: 2046 | B25: =B24*(1-(Inputs!B12+Scenario_Drivers!G4)) -> 2410826.9 | C25: =C24*(1-(Inputs!B13+Scenario_Drivers!H4)) -> 1343474 | D25: =D24*(1+(Inputs!B14+Scenario_Drivers!I4)) -> 706921.86 | E25: =IFERROR(D25/C25,0) -> 0.52618948 | F25: 0 | G25: =F25*Inputs!B33-Inputs!B32*Scenario_Drivers!F4 -> 0 | H25: =H24*(1-(Inputs!B12+Scenario_Drivers!G5))+L25 -> 2464258.8 | I25: =I24*(1-(Inputs!B13+Scenario_Drivers!H5))+L25+Inputs!B26*Scenario_Drivers!E5 -> 1403269 | J25: =J24*(1+(Inputs!B14+Scenario_Drivers!I5)) -> 706921.86 | K25: =IFERROR(J25/I25,0) -> 0.50376788 | L25: =((Inputs!B21+Inputs!B22+Inputs!B23)*Scenario_Drivers!B5)*(Inputs!B24*Scenario_Drivers!C5)-(Inputs!B25*Scenario_Drivers!D5) -> 2770 | M25: =L25*Inputs!B33 + Inputs!B26*Scenario_Drivers!E5*(Inputs!B30*Inputs!B31) - Inputs!B32*Scenario_Drivers!F5 -> 166204404000 | N25: =N24*(1-(Inputs!B12+Scenario_Drivers!G6))+R25 -> 2494552.5 | O25: =O24*(1-(Inputs!B13+Scenario_Drivers!H6))+R25+Inputs!B26*Scenario_Drivers!E6 -> 1434103.9 | P25: =P24*(1+(Inputs!B14+Scenario_Drivers!I6)) -> 706921.86 | Q25: =IFERROR(P25/O25,0) -> 0.49293631 | R25: =((Inputs!B21+Inputs!B22+Inputs!B23)*Scenario_Drivers!B6)*(Inputs!B24*Scenario_Drivers!C6)-(Inputs!B25*Scenario_Drivers!D6) -> 4340.475 | S25: =R25*Inputs!B33 + Inputs!B26*Scenario_Drivers!E6*(Inputs!B30*Inputs!B31) - Inputs!B32*Scenario_Drivers!F6 -> 260433785400 | T25: =T24*(1-(Inputs!B12+Scenario_Drivers!G7))+X25 -> 2326754.4 | U25: =U24*(1-(Inputs!B13+Scenario_Drivers!H7))+X25+Inputs!B26*Scenario_Drivers!E7 -> 1321710.7 | V25: =V24*(1+(Inputs!B14+Scenario_Drivers!I7)) -> 714299.06 | W25: =IFERROR(V25/U25,0) -> 0.54043524 | X25: =((Inputs!B21+Inputs!B22+Inputs!B23)*Scenario_Drivers!B7)*(Inputs!B24*Scenario_Drivers!C7)-(Inputs!B25*Scenario_Drivers!D7) -> 847.15 | Y25: =X25*Inputs!B33 + Inputs!B26*Scenario_Drivers!E7*(Inputs!B30*Inputs!B31) - Inputs!B32*Scenario_Drivers!F7 -> 50831640600
A26: 2047 | B26: =B25*(1-(Inputs!B12+Scenario_Drivers!G4)) -> 2390104.5 | C26: =C25*(1-(Inputs!B13+Scenario_Drivers!H4)) -> 1326667.7 | D26: =D25*(1+(Inputs!B14+Scenario_Drivers!I4)) -> 714808.44 | E26: =IFERROR(D26/C26,0) -> 0.5387999 | F26: 0 | G26: =F26*Inputs!B33-Inputs!B32*Scenario_Drivers!F4 -> 0 | H26: =H25*(1-(Inputs!B12+Scenario_Drivers!G5))+L26 -> 2445847.2 | I26: =I25*(1-(Inputs!B13+Scenario_Drivers!H5))+L26+Inputs!B26*Scenario_Drivers!E5 -> 1388934.8 | J26: =J25*(1+(Inputs!B14+Scenario_Drivers!I5)) -> 714808.44 | K26: =IFERROR(J26/I26,0) -> 0.51464507 | L26: =((Inputs!B21+Inputs!B22+Inputs!B23)*Scenario_Drivers!B5)*(Inputs!B24*Scenario_Drivers!C5)-(Inputs!B25*Scenario_Drivers!D5) -> 2770 | M26: =L26*Inputs!B33 + Inputs!B26*Scenario_Drivers!E5*(Inputs!B30*Inputs!B31) - Inputs!B32*Scenario_Drivers!F5 -> 166204404000 | N26: =N25*(1-(Inputs!B12+Scenario_Drivers!G6))+R26 -> 2477450.9 | O26: =O25*(1-(Inputs!B13+Scenario_Drivers!H6))+R26+Inputs!B26*Scenario_Drivers!E6 -> 1421044.4 | P26: =P25*(1+(Inputs!B14+Scenario_Drivers!I6)) -> 714808.44 | Q26: =IFERROR(P26/O26,0) -> 0.50301627 | R26: =((Inputs!B21+Inputs!B22+Inputs!B23)*Scenario_Drivers!B6)*(Inputs!B24*Scenario_Drivers!C6)-(Inputs!B25*Scenario_Drivers!D6) -> 4340.475 | S26: =R26*Inputs!B33 + Inputs!B26*Scenario_Drivers!E6*(Inputs!B30*Inputs!B31) - Inputs!B32*Scenario_Drivers!F6 -> 260433785400 | T26: =T25*(1-(Inputs!B12+Scenario_Drivers!G7))+X26 -> 2302948.3 | U26: =U25*(1-(Inputs!B13+Scenario_Drivers!H7))+X26+Inputs!B26*Scenario_Drivers!E7 -> 1304311.4 | V26: =V25*(1+(Inputs!B14+Scenario_Drivers!I7)) -> 722625.08 | W26: =IFERROR(V26/U26,0) -> 0.55402806 | X26: =((Inputs!B21+Inputs!B22+Inputs!B23)*Scenario_Drivers!B7)*(Inputs!B24*Scenario_Drivers!C7)-(Inputs!B25*Scenario_Drivers!D7) -> 847.15 | Y26: =X26*Inputs!B33 + Inputs!B26*Scenario_Drivers!E7*(Inputs!B30*Inputs!B31) - Inputs!B32*Scenario_Drivers!F7 -> 50831640600
A27: 2048 | B27: =B26*(1-(Inputs!B12+Scenario_Drivers!G4)) -> 2369560.3 | C27: =C26*(1-(Inputs!B13+Scenario_Drivers!H4)) -> 1310071.7 | D27: =D26*(1+(Inputs!B14+Scenario_Drivers!I4)) -> 722782.99 | E27: =IFERROR(D27/C27,0) -> 0.55171253 | F27: 0 | G27: =F27*Inputs!B33-Inputs!B32*Scenario_Drivers!F4 -> 0 | H27: =H26*(1-(Inputs!B12+Scenario_Drivers!G5))+L27 -> 2427593.8 | I27: =I26*(1-(Inputs!B13+Scenario_Drivers!H5))+L27+Inputs!B26*Scenario_Drivers!E5 -> 1374779.9 | J27: =J26*(1+(Inputs!B14+Scenario_Drivers!I5)) -> 722782.99 | K27: =IFERROR(J27/I27,0) -> 0.52574453 | L27: =((Inputs!B21+Inputs!B22+Inputs!B23)*Scenario_Drivers!B5)*(Inputs!B24*Scenario_Drivers!C5)-(Inputs!B25*Scenario_Drivers!D5) -> 2770 | M27: =L27*Inputs!B33 + Inputs!B26*Scenario_Drivers!E5*(Inputs!B30*Inputs!B31) - Inputs!B32*Scenario_Drivers!F5 -> 166204404000 | N27: =N26*(1-(Inputs!B12+Scenario_Drivers!G6))+R27 -> 2460496.4 | O27: =O26*(1-(Inputs!B13+Scenario_Drivers!H6))+R27+Inputs!B26*Scenario_Drivers!E6 -> 1408148.3 | P27: =P26*(1+(Inputs!B14+Scenario_Drivers!I6)) -> 722782.99 | Q27: =IFERROR(P27/O27,0) -> 0.51328615 | R27: =((Inputs!B21+Inputs!B22+Inputs!B23)*Scenario_Drivers!B6)*(Inputs!B24*Scenario_Drivers!C6)-(Inputs!B25*Scenario_Drivers!D6) -> 4340.475 | S27: =R27*Inputs!B33 + Inputs!B26*Scenario_Drivers!E6*(Inputs!B30*Inputs!B31) - Inputs!B32*Scenario_Drivers!F6 -> 260433785400 | T27: =T26*(1-(Inputs!B12+Scenario_Drivers!G7))+X27 -> 2279394.5 | U27: =U26*(1-(Inputs!B13+Scenario_Drivers!H7))+X27+Inputs!B26*Scenario_Drivers!E7 -> 1287155.7 | V27: =V26*(1+(Inputs!B14+Scenario_Drivers!I7)) -> 731048.16 | W27: =IFERROR(V27/U27,0) -> 0.56795627 | X27: =((Inputs!B21+Inputs!B22+Inputs!B23)*Scenario_Drivers!B7)*(Inputs!B24*Scenario_Drivers!C7)-(Inputs!B25*Scenario_Drivers!D7) -> 847.15 | Y27: =X27*Inputs!B33 + Inputs!B26*Scenario_Drivers!E7*(Inputs!B30*Inputs!B31) - Inputs!B32*Scenario_Drivers!F7 -> 50831640600
A28: 2049 | B28: =B27*(1-(Inputs!B12+Scenario_Drivers!G4)) -> 2349192.6 | C28: =C27*(1-(Inputs!B13+Scenario_Drivers!H4)) -> 1293683.4 | D28: =D27*(1+(Inputs!B14+Scenario_Drivers!I4)) -> 730846.52 | E28: =IFERROR(D28/C28,0) -> 0.56493462 | F28: 0 | G28: =F28*Inputs!B33-Inputs!B32*Scenario_Drivers!F4 -> 0 | H28: =H27*(1-(Inputs!B12+Scenario_Drivers!G5))+L28 -> 2409497.3 | I28: =I27*(1-(Inputs!B13+Scenario_Drivers!H5))+L28+Inputs!B26*Scenario_Drivers!E5 -> 1360802 | J28: =J27*(1+(Inputs!B14+Scenario_Drivers!I5)) -> 730846.52 | K28: =IFERROR(J28/I28,0) -> 0.53707042 | L28: =((Inputs!B21+Inputs!B22+Inputs!B23)*Scenario_Drivers!B5)*(Inputs!B24*Scenario_Drivers!C5)-(Inputs!B25*Scenario_Drivers!D5) -> 2770 | M28: =L28*Inputs!B33 + Inputs!B26*Scenario_Drivers!E5*(Inputs!B30*Inputs!B31) - Inputs!B32*Scenario_Drivers!F5 -> 166204404000 | N28: =N27*(1-(Inputs!B12+Scenario_Drivers!G6))+R28 -> 2443687.5 | O28: =O27*(1-(Inputs!B13+Scenario_Drivers!H6))+R28+Inputs!B26*Scenario_Drivers!E6 -> 1395413.5 | P28: =P27*(1+(Inputs!B14+Scenario_Drivers!I6)) -> 730846.52 | Q28: =IFERROR(P28/O28,0) -> 0.52374908 | R28: =((Inputs!B21+Inputs!B22+Inputs!B23)*Scenario_Drivers!B6)*(Inputs!B24*Scenario_Drivers!C6)-(Inputs!B25*Scenario_Drivers!D6) -> 4340.475 | S28: =R28*Inputs!B33 + Inputs!B26*Scenario_Drivers!E6*(Inputs!B30*Inputs!B31) - Inputs!B32*Scenario_Drivers!F6 -> 260433785400 | T28: =T27*(1-(Inputs!B12+Scenario_Drivers!G7))+X28 -> 2256090.2 | U28: =U27*(1-(Inputs!B13+Scenario_Drivers!H7))+X28+Inputs!B26*Scenario_Drivers!E7 -> 1270240.4 | V28: =V27*(1+(Inputs!B14+Scenario_Drivers!I7)) -> 739569.41 | W28: =IFERROR(V28/U28,0) -> 0.5822279 | X28: =((Inputs!B21+Inputs!B22+Inputs!B23)*Scenario_Drivers!B7)*(Inputs!B24*Scenario_Drivers!C7)-(Inputs!B25*Scenario_Drivers!D7) -> 847.15 | Y28: =X28*Inputs!B33 + Inputs!B26*Scenario_Drivers!E7*(Inputs!B30*Inputs!B31) - Inputs!B32*Scenario_Drivers!F7 -> 50831640600
A29: 2050 | B29: =B28*(1-(Inputs!B12+Scenario_Drivers!G4)) -> 2329000 | C29: =C28*(1-(Inputs!B13+Scenario_Drivers!H4)) -> 1277500 | D29: =D28*(1+(Inputs!B14+Scenario_Drivers!I4)) -> 739000 | E29: =IFERROR(D29/C29,0) -> 0.57847358 | F29: 0 | G29: =F29*Inputs!B33-Inputs!B32*Scenario_Drivers!F4 -> 0 | H29: =H28*(1-(Inputs!B12+Scenario_Drivers!G5))+L29 -> 2391556.3 | I29: =I28*(1-(Inputs!B13+Scenario_Drivers!H5))+L29+Inputs!B26*Scenario_Drivers!E5 -> 1346999 | J29: =J28*(1+(Inputs!B14+Scenario_Drivers!I5)) -> 739000 | K29: =IFERROR(J29/I29,0) -> 0.54862697 | L29: =((Inputs!B21+Inputs!B22+Inputs!B23)*Scenario_Drivers!B5)*(Inputs!B24*Scenario_Drivers!C5)-(Inputs!B25*Scenario_Drivers!D5) -> 2770 | M29: =L29*Inputs!B33 + Inputs!B26*Scenario_Drivers!E5*(Inputs!B30*Inputs!B31) - Inputs!B32*Scenario_Drivers!F5 -> 166204404000 | N29: =N28*(1-(Inputs!B12+Scenario_Drivers!G6))+R29 -> 2427023.2 | O29: =O28*(1-(Inputs!B13+Scenario_Drivers!H6))+R29+Inputs!B26*Scenario_Drivers!E6 -> 1382838 | P29: =P28*(1+(Inputs!B14+Scenario_Drivers!I6)) -> 739000 | Q29: =IFERROR(P29/O29,0) -> 0.53440823 | R29: =((Inputs!B21+Inputs!B22+Inputs!B23)*Scenario_Drivers!B6)*(Inputs!B24*Scenario_Drivers!C6)-(Inputs!B25*Scenario_Drivers!D6) -> 4340.475 | S29: =R29*Inputs!B33 + Inputs!B26*Scenario_Drivers!E6*(Inputs!B30*Inputs!B31) - Inputs!B32*Scenario_Drivers!F6 -> 260433785400 | T29: =T28*(1-(Inputs!B12+Scenario_Drivers!G7))+X29 -> 2233032.8 | U29: =U28*(1-(Inputs!B13+Scenario_Drivers!H7))+X29+Inputs!B26*Scenario_Drivers!E7 -> 1253562.1 | V29: =V28*(1+(Inputs!B14+Scenario_Drivers!I7)) -> 748190 | W29: =IFERROR(V29/U29,0) -> 0.59685116 | X29: =((Inputs!B21+Inputs!B22+Inputs!B23)*Scenario_Drivers!B7)*(Inputs!B24*Scenario_Drivers!C7)-(Inputs!B25*Scenario_Drivers!D7) -> 847.15 | Y29: =X29*Inputs!B33 + Inputs!B26*Scenario_Drivers!E7*(Inputs!B30*Inputs!B31) - Inputs!B32*Scenario_Drivers!F7 -> 50831640600

Sheet Summary
A1: Dashboard summary
A3: Metric | B3: Baseline | C3: Moderate | D3: Strong | E3: Stress
A4: Population, 2050 | B4: =Model!B29 -> 2329000 | C4: =Model!H29 -> 2391556.3 | D4: =Model!N29 -> 2427023.2 | E4: =Model!T29 -> 2233032.8
A5: Working-age population, 2050 | B5: =Model!C29 -> 1277500 | C5: =Model!I29 -> 1346999 | D5: =Model!O29 -> 1382838 | E5: =Model!U29 -> 1253562.1
A6: Old-age population, 2050 | B6: =Model!D29 -> 739000 | C6: =Model!J29 -> 739000 | D6: =Model!P29 -> 739000 | E6: =Model!V29 -> 748190
A7: Old-age dependency ratio, 2050 | B7: =Model!E29 -> 0.57847358 | C7: =Model!K29 -> 0.54862697 | D7: =Model!Q29 -> 0.53440823 | E7: =Model!W29 -> 0.59685116
A8: Net retained contributors / year | B8: =AVERAGE(Model!F4:F29) -> #DIV/0! | C8: =AVERAGE(Model!L4:L29) -> 2770 | D8: =AVERAGE(Model!R4:R29) -> 4340.475 | E8: =AVERAGE(Model!X4:X29) -> 847.15
A11: Model logic
A12: Baseline is calibrated to the EC / Eurostat-style Lithuania path. Policy scenarios change only the variables the policy is meant to affect: inflows, retention, exits, and a small parent labor-force effect.
G13: Year | H13: Baseline | I13: Moderate | J13: Strong | K13: Stress
G14: =Model!A4 -> 2025 | H14: =Model!B4 -> 2890000 | I14: =Model!H4 -> 2890000 | J14: =Model!N4 -> 2890000 | K14: =Model!T4 -> 2890000
G15: =Model!A5 -> 2026 | H15: =Model!B5 -> 2865158.9 | I15: =Model!H5 -> 2867928.9 | J15: =Model!N5 -> 2869499.3 | K15: =Model!T5 -> 2860226
G16: =Model!A6 -> 2027 | H16: =Model!B6 -> 2840531.3 | I16: =Model!H6 -> 2846047.5 | J16: =Model!N6 -> 2849174.9 | K16: =Model!T6 -> 2830767.5
G17: =Model!A7 -> 2028 | H17: =Model!B7 -> 2816115.4 | I17: =Model!H7 -> 2824354.1 | J17: =Model!N7 -> 2829025.2 | K17: =Model!T7 -> 2801621.1
G18: =Model!A8 -> 2029 | H18: =Model!B8 -> 2791909.3 | I18: =Model!H8 -> 2802847.3 | J18: =Model!N8 -> 2809048.6 | K18: =Model!T8 -> 2772783.6
G19: =Model!A9 -> 2030 | H19: =Model!B9 -> 2767911.3 | I19: =Model!H9 -> 2781525.3 | J19: =Model!N9 -> 2789243.8 | K19: =Model!T9 -> 2744251.6
G20: =Model!A10 -> 2031 | H20: =Model!B10 -> 2744119.6 | I20: =Model!H10 -> 2760386.5 | J20: =Model!N10 -> 2769609.2 | K20: =Model!T10 -> 2716021.9
G21: =Model!A11 -> 2032 | H21: =Model!B11 -> 2720532.4 | I21: =Model!H11 -> 2739429.5 | J21: =Model!N11 -> 2750143.4 | K21: =Model!T11 -> 2688091.3
G22: =Model!A12 -> 2033 | H22: =Model!B12 -> 2697147.9 | I22: =Model!H12 -> 2718652.6 | J22: =Model!N12 -> 2730844.9 | K22: =Model!T12 -> 2660456.7
G23: =Model!A13 -> 2034 | H23: =Model!B13 -> 2673964.5 | I23: =Model!H13 -> 2698054.3 | J23: =Model!N13 -> 2711712.2 | K23: =Model!T13 -> 2633114.8
G24: =Model!A14 -> 2035 | H24: =Model!B14 -> 2650980.3 | I24: =Model!H14 -> 2677633.1 | J24: =Model!N14 -> 2692744.1 | K24: =Model!T14 -> 2606062.7
G25: =Model!A15 -> 2036 | H25: =Model!B15 -> 2628193.7 | I25: =Model!H15 -> 2657387.3 | J25: =Model!N15 -> 2673938.9 | K25: =Model!T15 -> 2579297.2
... G39: =Model!A29 -> 2050 | H39: =Model!B29 -> 2329000 | I39: =Model!H29 -> 2391556.3 | J39: =Model!N29 -> 2427023.2 | K39: =Model!T29 -> 2233032.8
G43: Scenario | H43: Ratio
G44: Baseline | H44: =Model!E29 -> 0.57847358
G45: Moderate | H45: =Model!K29 -> 0.54862697
G46: Strong | H46: =Model!Q29 -> 0.53440823
G47: Stress | H47: =Model!W29 -> 0.59685116

Sheet Notes
A1: How the model works
A3: 1. Baseline path: the workbook anchors the no-policy baseline to the European Commission / Eurostat-style Lithuania 2050 path (population ~2.329m; old-age dependency ratio ~57.9).
A4: 2. Policy engine: Net retained contributors = (immigrants + returnees + retained graduates) × retention rate − exits.
A5: 3. Population update: next year's population = this year's population × (1 − baseline decline) + net retained contributors.
A6: 4. Working-age update: next year's working-age population = this year's working-age population × (1 − baseline decline) + net retained contributors + a small parent labor-force effect.
A7: 5. Dependency ratio = old-age population ÷ working-age population.
A8: 6. Scenarios: Moderate, Strong, and Stress vary only policy-relevant parameters such as inflows, retention, exits, and background conditions.
A9: 7. Interpretation: this is a benchmarked scenario model, not a forecast.
